instascrape/__init__.py
instascrape/core/__init__.py
instascrape/core/_mappings.py
instascrape/core/_static_scraper.py
instascrape/core/json_algos.py
instascrape/exceptions/__init__.py
instascrape/exceptions/exceptions.py
instascrape/scrapers/__init__.py
instascrape/scrapers/comment.py
instascrape/scrapers/hashtag.py
instascrape/scrapers/igtv.py
instascrape/scrapers/location.py
instascrape/scrapers/post.py
instascrape/scrapers/profile.py
instascrape/scrapers/reel.py
instascrape/scrapers/scrape_tools.py
insta_scrape-2.1.2.dist-info/LICENSE
insta_scrape-2.1.2.dist-info/METADATA
insta_scrape-2.1.2.dist-info/WHEEL
insta_scrape-2.1.2.dist-info/top_level.txt
insta_scrape-2.1.2.dist-info/RECORD
