Metadata-Version: 2.1
Name: insta-scrape
Version: 2.1.2
Summary: Super lightweight Instagram web scraper for data analysis
Home-page: https://github.com/chris-greening/instascrape
Author: Chris Greening
Author-email: chris@christophergreening.com
License: UNKNOWN
Platform: UNKNOWN
Classifier: Programming Language :: Python :: 3
Classifier: License :: OSI Approved :: MIT License
Classifier: Operating System :: OS Independent
Requires-Python: >=3.7
